microsoft_agents/activity/__init__.py
microsoft_agents/activity/_load_configuration.py
microsoft_agents/activity/_type_aliases.py
microsoft_agents/activity/action_types.py
microsoft_agents/activity/activity.py
microsoft_agents/activity/activity_event_names.py
microsoft_agents/activity/activity_importance.py
microsoft_agents/activity/activity_types.py
microsoft_agents/activity/adaptive_card_invoke_action.py
microsoft_agents/activity/adaptive_card_invoke_response.py
microsoft_agents/activity/adaptive_card_invoke_value.py
microsoft_agents/activity/agents_model.py
microsoft_agents/activity/ai_entity.py
microsoft_agents/activity/animation_card.py
microsoft_agents/activity/attachment.py
microsoft_agents/activity/attachment_data.py
microsoft_agents/activity/attachment_info.py
microsoft_agents/activity/attachment_layout_types.py
microsoft_agents/activity/attachment_view.py
microsoft_agents/activity/audio_card.py
microsoft_agents/activity/basic_card.py
microsoft_agents/activity/caller_id_constants.py
microsoft_agents/activity/card_action.py
microsoft_agents/activity/card_image.py
microsoft_agents/activity/channel_account.py
microsoft_agents/activity/channel_adapter_protocol.py
microsoft_agents/activity/channels.py
microsoft_agents/activity/contact_relation_update_action_types.py
microsoft_agents/activity/conversation_account.py
microsoft_agents/activity/conversation_members.py
microsoft_agents/activity/conversation_parameters.py
microsoft_agents/activity/conversation_reference.py
microsoft_agents/activity/conversation_resource_response.py
microsoft_agents/activity/conversation_update_types.py
microsoft_agents/activity/conversations_result.py
microsoft_agents/activity/delivery_modes.py
microsoft_agents/activity/end_of_conversation_codes.py
microsoft_agents/activity/entity.py
microsoft_agents/activity/error.py
microsoft_agents/activity/error_response.py
microsoft_agents/activity/expected_replies.py
microsoft_agents/activity/fact.py
microsoft_agents/activity/geo_coordinates.py
microsoft_agents_activity-0.3.2.dist-info/METADATA
microsoft_agents_activity-0.3.2.dist-info/WHEEL
microsoft_agents_activity-0.3.2.dist-info/top_level.txt
microsoft_agents_activity-0.3.2.dist-info/RECORD
